splunk_as/__init__.py
splunk_as/autocomplete_cache.py
splunk_as/config_manager.py
splunk_as/credential_manager.py
splunk_as/error_handler.py
splunk_as/formatters.py
splunk_as/job_poller.py
splunk_as/py.typed
splunk_as/search_context.py
splunk_as/spl_helper.py
splunk_as/splunk_client.py
splunk_as/time_utils.py
splunk_as/validators.py
splunk_as/cli/__init__.py
splunk_as/cli/cli_utils.py
splunk_as/cli/main.py
splunk_as/cli/commands/__init__.py
splunk_as/cli/commands/admin_cmds.py
splunk_as/cli/commands/alert_cmds.py
splunk_as/cli/commands/app_cmds.py
splunk_as/cli/commands/config_cmds.py
splunk_as/cli/commands/dashboard_cmds.py
splunk_as/cli/commands/export_cmds.py
splunk_as/cli/commands/input_cmds.py
splunk_as/cli/commands/job_cmds.py
splunk_as/cli/commands/kvstore_cmds.py
splunk_as/cli/commands/lookup_cmds.py
splunk_as/cli/commands/metadata_cmds.py
splunk_as/cli/commands/metrics_cmds.py
splunk_as/cli/commands/savedsearch_cmds.py
splunk_as/cli/commands/search_cmds.py
splunk_as/cli/commands/security_cmds.py
splunk_as/cli/commands/tag_cmds.py
splunk_as/cli/commands/user_cmds.py
splunk_as/mock/__init__.py
splunk_as/mock/base.py
splunk_as/mock/client.py
splunk_as/mock/factories.py
splunk_as/mock/protocols.py
splunk_as/mock/mixins/__init__.py
splunk_as/mock/mixins/admin.py
splunk_as/mock/mixins/export.py
splunk_as/mock/mixins/job.py
splunk_as/mock/mixins/metadata.py
splunk_as/mock/mixins/search.py
splunk_as-1.1.6.dist-info/METADATA
splunk_as-1.1.6.dist-info/WHEEL
splunk_as-1.1.6.dist-info/entry_points.txt
splunk_as-1.1.6.dist-info/licenses/LICENSE
splunk_as-1.1.6.dist-info/RECORD
